Librarymu/__init__.py
Librarymu/golden_ratio.py
gold33423315-0.0.1.dist-info/LICENCE.txt
gold33423315-0.0.1.dist-info/METADATA
gold33423315-0.0.1.dist-info/WHEEL
gold33423315-0.0.1.dist-info/top_level.txt
gold33423315-0.0.1.dist-info/RECORD
