Metadata-Version: 2.1
Name: gold33423315
Version: 0.0.1
Summary: Buat Uas
Home-page: https://github.com/codewithwan/gold33423315
Author: codewithwan
Author-email: <deezerxstore@gmail.com>
License: MIT
Keywords: UAS,COY
Classifier: Development Status :: 1 - Planning
License-File: LICENCE.txt
